AUTHORS
ChangeLog
LICENSE
README.rst
requirements.txt
setup.cfg
setup.py
test-requirements.txt
tox.ini
pocket2pinboard/__init__.py
pocket2pinboard/auth.py
pocket2pinboard/bookmarks.py
pocket2pinboard/cmd.py
pocket2pinboard/config.py
pocket2pinboard/keys.py
pocket2pinboard/retrieve.py
pocket2pinboard.egg-info/PKG-INFO
pocket2pinboard.egg-info/SOURCES.txt
pocket2pinboard.egg-info/dependency_links.txt
pocket2pinboard.egg-info/entry_points.txt
pocket2pinboard.egg-info/not-zip-safe
pocket2pinboard.egg-info/pbr.json
pocket2pinboard.egg-info/requires.txt
pocket2pinboard.egg-info/top_level.txt