Metadata-Version: 1.1
Name: pocket2pinboard
Version: 0.1.0
Summary: Import pocket articles into pinboard.in
Home-page: http://pypi.python.org/pypi/pocket2pinboard
Author: Doug Hellmann
Author-email: doug@doughellmann.com
License: UNKNOWN
Platform: UNKNOWN
Classifier: Development Status :: 3 - Alpha
Classifier: Environment :: Console
Classifier: License :: OSI Approved :: Apache Software License
Classifier: Operating System :: OS Independent
Classifier: Programming Language :: Python
Classifier: Programming Language :: Python :: 2
Classifier: Programming Language :: Python :: 2.7
